{
  "users": [
    {
      "email": "sadfas@asdf.com",
      "password": "$2a$10$CHhjIN1MxrLxhpEV1c4.X.4vbOa.vYazG5cPp3TzlZG8gmCzkUYdq",
      "name": "마르코",
      "id": 1
    },
    {
      "email": "a@b.com",
      "password": "$2a$10$SN6Pyeg/5IcOvvEU9gSg.u.1dNav5q.qtkDX7Df/TS63brBfR3yb2",
      "name": "마르코",
      "id": 2
    },
    {
      "email": "haha@gamilc.com",
      "password": "$2a$10$hnWu07kUqAUZReUrOZwLyOE8Ys4mNoZv3b/1WQlyK4E4Dm7Aj4Fp6",
      "name": "하하",
      "id": 3
    },
    {
      "email": "marco@gmail.com",
      "password": "$2a$10$A.dhG9EcPC83DR5lvxRhhuFiLK4qR8RHNfCvbg/kDmYTF8gGDTjLS",
      "name": "마르코",
      "id": 4
    },
    {
      "email": "wow@gmail.com",
      "password": "$2a$10$8T9OBvBmdu5oMzi36AECfOjwHW9CP2/BSLRrvmDsPZMUoRTcw0sWe",
      "name": "wowwww",
      "id": 5
    },
    {
      "email": "1@1.com",
      "password": "$2a$10$6wwwUaQDtUbnZAGFhjv6quZk.nmppAkJye4T.fyy5Yn/RtvU.YRQ.",
      "name": "123",
      "id": 6
    },
    {
      "email": "2@2.com",
      "password": "$2a$10$bF/yMb.TMKfA0ZRtIPmGIOZh6qb.p.RrY3BBPat74aLqjEwbE0Pba",
      "name": "asdfasdf",
      "id": 7
    }
  ]
}