{
  "users": [
    {
      "email": "olivier@mail.com",
      "password": "$2a$10$7.GbHSFeVvlMd2wzQ9wvLOME2fDp8ypQ.ZfVxrappWGWGylJBHtyi",
      "id": 1
    },
    {
      "email": "123@123",
      "name": "온스타",
      "password": "$2a$10$JqSe21vVPpBNOCe/eJ2I/OSy47KfJXCs5SxngDmFMyYr6/4tRyyyy",
      "id": 2
    },
    {
      "email": "123@123",
      "password": "$2a$10$KO1vnd.JAkQ8Ui5MrdyebO0TTIfARf/XPemYGfkjtO9lIOUnCU3q6",
      "name": "123",
      "id": 3
    },
    {
      "email": "123@123",
      "password": "$2a$10$obFT6faJy6aNk0vRp7e7Pu5O6swKj1KIzAhoQDIU5ujE39.8DmKxu",
      "name": "123",
      "id": 4
    },
    {
      "email": "222@222",
      "password": "$2a$10$u1gn3S/R5WklYhOVv2TvtemvSkhhDGzy/K3FOar64oAGTa/qOHGJi",
      "name": "222",
      "id": 5
    },
    {
      "email": "222@222",
      "password": "$2a$10$SUsZz68koFW7hD8nPI266.ovnRYils8Fgs.nlUUirNhA/hFe1pFXi",
      "name": "222",
      "id": 6
    },
    {
      "email": "123@123123",
      "password": "$2a$10$xmYxB2hfPEBW7tjQOpWXO.iquEl3Dqft4mXN/zwW9CuidJ2sy0Tzm",
      "name": "1231",
      "id": 7
    },
    {
      "email": "cks3066@naver.com",
      "password": "$2a$10$fmXGXFWdabXBfsz0sopR1uk3yPOF1IJWLHXMcgk5V4OXqYMPxR.oC",
      "name": "온승찬",
      "id": 8
    },
    {
      "email": "c1ks3066@naver.com",
      "password": "$2a$10$1sg0n3i67.Fecyi497cGbuKceJFVebz.wuv87UUxLcO2gEeYpyPsy",
      "name": "온승찬",
      "id": 9
    },
    {
      "email": "on2130@naver.com",
      "password": "$2a$10$ZN/sTGgcBpS1vgvNDL3J9udeIhz4ULDhfv6AztiZ588OVwyCwklzK",
      "name": "on9843",
      "id": 10
    }
  ]
}